predflow/__init__.py
predflow/datasets_utils.py
predflow/pc_utils.py
predflow/precision_modulated_supervised_autodiff_pc.py
predflow/precision_modulated_supervised_explicit_pc.py
predflow/precisions_utils.py
predflow/supervised_autodiff_pc.py
predflow/supervised_fullyconnected_stricthierarchy_explicit_pc.py
predflow/tf_utils.py
predflow-0.0.10.dist-info/LICENSE
predflow-0.0.10.dist-info/METADATA
predflow-0.0.10.dist-info/WHEEL
predflow-0.0.10.dist-info/top_level.txt
predflow-0.0.10.dist-info/RECORD
